piecash2/__init__.py
piecash2/__main__.py
piecash2/cli.py
piecash2/utils.py
piecash2/core/__init__.py
piecash2/core/book.py
piecash2/schema/__init__.py
piecash2/schema/generated/__init__.py
piecash2/schema/generation/__init__.py
piecash2/schema/generation/sa_schema_post.py
piecash2/schema/generation/sa_schema_pre.py
piecash2/schema/generation/schema_generation.py
piecash2-0.1.3.dist-info/LICENSE
piecash2-0.1.3.dist-info/METADATA
piecash2-0.1.3.dist-info/WHEEL
piecash2-0.1.3.dist-info/entry_points.txt
piecash2-0.1.3.dist-info/top_level.txt
piecash2-0.1.3.dist-info/RECORD
