Metadata-Version: 2.1
Name: piecash2
Version: 0.1.3
Summary: piecash2, a python library to work with [GnuCash](https://www.gnucash.org/) books
Home-page: https://github.com/sdementen/piecash2/
Author: sdementen
License-File: LICENSE
Requires-Dist: sqlacodegen-v2
Provides-Extra: test
Requires-Dist: pytest ; extra == 'test'
Requires-Dist: coverage ; extra == 'test'
Requires-Dist: flake8 ; extra == 'test'
Requires-Dist: black ; extra == 'test'
Requires-Dist: isort ; extra == 'test'
Requires-Dist: pytest-cov ; extra == 'test'
Requires-Dist: mypy ; extra == 'test'
Requires-Dist: gitchangelog ; extra == 'test'
Requires-Dist: mkdocs ; extra == 'test'
Requires-Dist: typer ; extra == 'test'
